{
	"_meta": {
		"otherSources": {
			"monster": {
				"XMM": "LFL"
			}
		}
	},
	"monster": [
		{
			"name": "Incarnation of Transience",
			"group": [
				"Incarnation of Nature"
			],
			"source": "LFL",
			"size": [
				"H"
			],
			"type": "fey",
			"alignment": [
				"N"
			],
			"ac": [
				16
			],
			"hp": {
				"average": 142,
				"formula": "15d12 + 45"
			},
			"speed": {
				"walk": 40,
				"swim": 40
			},
			"initiative": {
				"proficiency": 1
			},
			"str": 21,
			"dex": 20,
			"con": 17,
			"int": 10,
			"wis": 14,
			"cha": 16,
			"save": {
				"dex": "+8",
				"con": "+6"
			},
			"senses": [
				"Darkvision 60 ft."
			],
			"passive": 12,
			"conditionImmune": [
				"grappled",
				"paralyzed",
				"petrified",
				"prone",
				"restrained"
			],
			"languages": [
				"Sylvan; telepathy 120 ft."
			],
			"cr": "7",
			"trait": [
				{
					"name": "Ephemeral Movement",
					"entries": [
						"L'incarnazione può muoversi attraverso altre creature e oggetti come se lo fossero {@variantrule Difficult Terrain|XPHB} e il suo movimento non provoca Attacchi di Opportunità. Subisce 5 ({@damage 1d10}) danni Forza se termina il suo turno all'interno di un oggetto."
					]
				},
				{
					"name": "Magic Resistance",
					"entries": [
						"L'incarnazione ha {@variantrule Advantage|XPHB} sui tiri salvezza contro incantesimi e altri effetti magici."
					]
				}
			],
			"action": [
				{
					"name": "Multiattack",
					"entries": [
						"L'incarnazione effettua tre attacchi, usando Morso o Globulo Miasmico in qualsiasi combinazione."
					]
				},
				{
					"name": "Bite",
					"entries": [
						"{@atkr m} {@hit 8}, portata 5 piedi {@h}14 ({@damage 2d8 + 5}) Danno perforante."
					]
				},
				{
					"name": "Miasmic Globule",
					"entries": [
						"{@atkr r} {@hit 8}, portata 60/120 piedi. {@h}15 ({@damage 6d4}) Danni da acido e il danno da acido {@variantrule Speed|XPHB} del bersaglio viene ridotto di 3 metri fino alla fine del turno successivo dell'incarnazione."
					]
				},
				{
					"name": "Spectral Stampede",
					"entries": [
						"L'incarnazione si muove fino a 80 piedi in linea retta. Ogni creatura nel cui spazio entra l'incarnazione viene presa di mira una volta dal seguente effetto. {@actSave dex} {@dc 16}. {@actSaveFail} 18 ({@damage 4d8}) Danno di forza. Se il bersaglio ha le stesse dimensioni dell'incarnazione o è inferiore, ha la condizione {@condition Prone|XPHB}. {@actSaveSuccess} Solo metà del danno."
					]
				}
			],
			"bonus": [
				{
					"name": "Shape-Shift",
					"entries": [
						"L'incarnazione cambia la sua taglia in Media, Grande o Enorme."
					]
				}
			],
			"environment": [
				"planar, feywild"
			],
			"traitTags": [
				"Magic Resistance"
			],
			"senseTags": [
				"D"
			],
			"actionTags": [
				"Multiattack"
			],
			"languageTags": [
				"S",
				"TP"
			],
			"damageTags": [
				"A",
				"O",
				"P"
			],
			"miscTags": [
				"MA",
				"RA"
			],
			"conditionInflict": [
				"prone"
			],
			"savingThrowForced": [
				"dexterity"
			],
			"hasToken": true,
			"hasFluff": true,
			"hasFluffImages": true
		},
		{
			"name": "Incarnation of Vibrance",
			"group": [
				"Incarnation of Nature"
			],
			"source": "LFL",
			"size": [
				"H"
			],
			"type": "fey",
			"alignment": [
				"N"
			],
			"ac": [
				14
			],
			"hp": {
				"average": 230,
				"formula": "20d12 + 100"
			},
			"speed": {
				"walk": 40
			},
			"initiative": {
				"proficiency": 1
			},
			"str": 20,
			"dex": 17,
			"con": 20,
			"int": 10,
			"wis": 16,
			"cha": 21,
			"save": {
				"con": "+9",
				"cha": "+9"
			},
			"senses": [
				"Darkvision 60 ft."
			],
			"passive": 13,
			"resist": [
				"radiant"
			],
			"conditionImmune": [
				"blinded",
				"charmed",
				"deafened",
				"frightened"
			],
			"languages": [
				"Sylvan; telepathy 120 ft."
			],
			"cr": "10",
			"spellcasting": [
				{
					"name": "Spellcasting",
					"type": "spellcasting",
					"headerEntries": [
						"L'incarnazione lancia uno dei seguenti incantesimi, che non richiedono componenti di incantesimi e utilizzano Carisma come capacità di lancio degli incantesimi:"
					],
					"will": [
						"{@spell Daylight|XPHB}",
						"{@spell Druidcraft|XPHB}",
						"{@spell Plant Growth|XPHB}"
					],
					"daily": {
						"1": [
							"{@spell Blindness/Deafness|XPHB}"
						]
					},
					"ability": "cha",
					"displayAs": "action"
				}
			],
			"trait": [
				{
					"name": "Magic Resistance",
					"entries": [
						"L'incarnazione ha {@variantrule Advantage|XPHB} sui tiri salvezza contro incantesimi e altri effetti magici."
					]
				}
			],
			"action": [
				{
					"name": "Multiattack",
					"entries": [
						"L'incarnazione effettua due attacchi Vine e usa Radiant Blast. Può sostituire un attacco della vite con l'uso del lancio di incantesimi {@spell Blindness/Deafness|XPHB} se disponibile."
					]
				},
				{
					"name": "Vine",
					"entries": [
						"{@atkr m} {@hit 9}, portata 20 piedi {@h}18 ({@damage 3d8 + 5}) Danni contundenti. Se il bersaglio ha le stesse dimensioni dell'incarnazione o è inferiore, ha la condizione {@condition Grappled|XPHB} (fuga {@dc 15}) da uno dei due rampicanti."
					]
				},
				{
					"name": "Radiant Blast",
					"entries": [
						"{@actSave con} {@dc 17}, ogni creatura scelta dall'incarnazione in un raggio di 20 piedi {@variantrule Emanation [Area of Effect]|XPHB|Emanation} originaria dell'incarnazione. {@actSaveFail} La creatura subisce 14 ({@damage 2d8 + 5}) danni radiosi. {@actSaveSuccess} Danno dimezzato."
					]
				}
			],
			"bonus": [
				{
					"name": "Shape-Shift",
					"entries": [
						"L'incarnazione cambia la sua taglia in Media, Grande o Enorme."
					]
				},
				{
					"name": "Teleport",
					"entries": [
						"L'incarnazione si teletrasporta fino a 18 metri in uno spazio non occupato che può vedere. L'incarnazione non può teletrasportarsi mentre ha una creatura {@condition Grappled|XPHB}."
					]
				}
			],
			"environment": [
				"planar, feywild"
			],
			"traitTags": [
				"Magic Resistance"
			],
			"senseTags": [
				"D"
			],
			"actionTags": [
				"Multiattack",
				"Teleport"
			],
			"languageTags": [
				"S",
				"TP"
			],
			"damageTags": [
				"B",
				"R"
			],
			"spellcastingTags": [
				"O"
			],
			"miscTags": [
				"MA",
				"RCH"
			],
			"conditionInflict": [
				"grappled"
			],
			"conditionInflictSpell": [
				"blinded",
				"deafened"
			],
			"savingThrowForced": [
				"constitution"
			],
			"savingThrowForcedSpell": [
				"constitution"
			],
			"hasToken": true,
			"hasFluff": true,
			"hasFluffImages": true
		},
		{
			"name": "Lorwyn Giant",
			"source": "LFL",
			"size": [
				"H"
			],
			"type": "giant",
			"alignment": [
				"C",
				"N"
			],
			"ac": [
				13
			],
			"hp": {
				"average": 115,
				"formula": "11d12 + 44"
			},
			"speed": {
				"walk": 40
			},
			"str": 21,
			"dex": 13,
			"con": 18,
			"int": 9,
			"wis": 16,
			"cha": 8,
			"save": {
				"con": "+7",
				"wis": "+6"
			},
			"passive": 13,
			"languages": [
				"Common",
				"Giant"
			],
			"cr": "6",
			"action": [
				{
					"name": "Multiattack",
					"entries": [
						"Il gigante effettua due attacchi, usando Stone Sword o Boulder in qualsiasi combinazione."
					]
				},
				{
					"name": "Stone Sword",
					"entries": [
						"{@atkr m} {@hit 8}, portata 15 piedi {@h}21 ({@damage 3d10 + 5}) Danno tagliente."
					]
				},
				{
					"name": "Boulder",
					"entries": [
						"{@atkr r} {@hit 8}, portata 60/240 piedi. {@h}14 ({@damage 2d8 + 5}) Danni contundenti. Se il bersaglio è una creatura Grande o più piccola, ha la condizione {@condition Prone|XPHB}."
					]
				}
			],
			"bonus": [
				{
					"name": "Name Sleep {@recharge 5}",
					"entries": [
						"Il gigante cade in un sonno profondo e ristoratore. Il gigante guadagna 20 {@variantrule Temporary Hit Points|XPHB} e mantiene la condizione {@condition Unconscious|XPHB} finché non subisce danni o fino alla fine del suo turno successivo. Il gigante ha {@variantrule Advantage|XPHB} sulle prove di abilità e sui tiri salvezza per 1 minuto."
					]
				}
			],
			"environment": [
				"planar, feywild"
			],
			"treasure": [
				"arcana"
			],
			"actionTags": [
				"Multiattack"
			],
			"languageTags": [
				"C",
				"GI"
			],
			"damageTags": [
				"B",
				"S"
			],
			"miscTags": [
				"MA",
				"RA",
				"RCH"
			],
			"conditionInflict": [
				"prone",
				"unconscious"
			],
			"hasToken": true,
			"hasFluff": true,
			"hasFluffImages": true
		},
		{
			"name": "Merrow Doublespeaker",
			"source": "LFL",
			"size": [
				"M"
			],
			"type": "monstrosity",
			"alignment": [
				"L",
				"E"
			],
			"ac": [
				14
			],
			"hp": {
				"average": 67,
				"formula": "9d8 + 27"
			},
			"speed": {
				"walk": 20,
				"swim": 40
			},
			"str": 18,
			"dex": 17,
			"con": 16,
			"int": 12,
			"wis": 13,
			"cha": 16,
			"save": {
				"dex": "+5",
				"cha": "+5"
			},
			"skill": {
				"deception": "+5",
				"stealth": "+5"
			},
			"senses": [
				"Darkvision 120 ft."
			],
			"passive": 11,
			"languages": [
				"Common",
				"Primordial (Aquan)"
			],
			"cr": "4",
			"spellcasting": [
				{
					"name": "Spellcasting",
					"type": "spellcasting",
					"headerEntries": [
						"Il merrow lancia uno dei seguenti incantesimi, che non richiede componenti materiali e utilizza Carisma come capacità di lancio degli incantesimi (salvezza incantesimo {@dc 13}):"
					],
					"will": [
						"{@spell Command|XPHB}",
						"{@spell Mage Hand|XPHB}",
						"{@spell Minor Illusion|XPHB}"
					],
					"ability": "cha",
					"displayAs": "action"
				}
			],
			"trait": [
				{
					"name": "Amphibious",
					"entries": [
						"Il merrow può respirare aria e acqua."
					]
				},
				{
					"name": "Mimicry",
					"entries": [
						"Il merrow può imitare voci e versi degli animali. Una creatura che sente le imitazioni può dire che sono imitazioni con una prova riuscita di Saggezza ({@skill Insight|XPHB} {@dc 15}."
					]
				}
			],
			"action": [
				{
					"name": "Multiattack",
					"entries": [
						"Il merrow effettua tre attacchi Spined Tail. Può sostituire uno di questi attacchi con l'uso del lancio di incantesimi {@spell Command|XPHB}."
					]
				},
				{
					"name": "Spined Tail",
					"entries": [
						"{@atkr m,r} {@hit 6}, portata 5 piedi o portata 20/60 piedi {@h}14 ({@damage 3d6 + 4}) Danno perforante."
					]
				}
			],
			"environment": [
				"planar, feywild"
			],
			"treasure": [
				"individual"
			],
			"traitTags": [
				"Amphibious",
				"Mimicry"
			],
			"senseTags": [
				"SD"
			],
			"actionTags": [
				"Multiattack"
			],
			"languageTags": [
				"AQ",
				"C",
				"P"
			],
			"damageTags": [
				"P"
			],
			"spellcastingTags": [
				"O"
			],
			"miscTags": [
				"MA",
				"RA"
			],
			"conditionInflictSpell": [
				"prone"
			],
			"savingThrowForcedSpell": [
				"wisdom"
			],
			"hasToken": true,
			"hasFluff": true,
			"hasFluffImages": true
		},
		{
			"name": "Merrow Haranguer",
			"source": "LFL",
			"size": [
				"M"
			],
			"type": "monstrosity",
			"alignment": [
				"L",
				"N"
			],
			"ac": [
				14
			],
			"hp": {
				"average": 90,
				"formula": "12d8 + 36"
			},
			"speed": {
				"walk": 5,
				"swim": 40
			},
			"str": 18,
			"dex": 18,
			"con": 16,
			"int": 14,
			"wis": 15,
			"cha": 19,
			"save": {
				"dex": "+7",
				"cha": "+7"
			},
			"skill": {
				"performance": "+7",
				"persuasion": "+7"
			},
			"passive": 12,
			"languages": [
				"Common",
				"Primordial (Aquan)"
			],
			"cr": "5",
			"trait": [
				{
					"name": "Amphibious",
					"entries": [
						"Il merrow può respirare aria e acqua."
					]
				}
			],
			"action": [
				{
					"name": "Multiattack",
					"entries": [
						"Il merrow effettua tre attacchi, usando Coral Scepter e {@condition Poisoned|XPHB} Longbow in qualsiasi combinazione."
					]
				},
				{
					"name": "Coral Scepter",
					"entries": [
						"{@atkr m} {@hit 7}, portata 5 piedi {@h}14 ({@damage 2d10 + 4}) Danni contundenti."
					]
				},
				{
					"name": "Poisoned Longbow",
					"entries": [
						"{@atkr r} {@hit 7}, portata 150/600 piedi. {@h}8 ({@damage 1d8 + 4}) Danni perforanti più 7 ({@damage 2d6}) Danni da veleno."
					]
				},
				{
					"name": "Invective",
					"entries": [
						"{@actSave wis} {@dc 15}, fino a tre creature che il merrow può vedere entro 18 metri. {@actSaveFail} 14 ({@damage 4d6}) Danni psichici e la creatura ha {@variantrule Disadvantage|XPHB} sul suo prossimo tiro per colpire prima della fine del turno successivo del merrow. {@actSaveSuccess} Solo metà del danno."
					]
				}
			],
			"environment": [
				"planar, feywild"
			],
			"treasure": [
				"individual"
			],
			"traitTags": [
				"Amphibious"
			],
			"actionTags": [
				"Multiattack"
			],
			"languageTags": [
				"AQ",
				"C",
				"P"
			],
			"damageTags": [
				"B",
				"I",
				"P",
				"Y"
			],
			"miscTags": [
				"MA",
				"RA",
				"RNG"
			],
			"savingThrowForced": [
				"wisdom"
			],
			"hasToken": true,
			"hasFluff": true,
			"hasFluffImages": true
		},
		{
			"name": "Noggle Ransacker",
			"source": "LFL",
			"size": [
				"S"
			],
			"type": "fey",
			"alignment": [
				"C",
				"N"
			],
			"ac": [
				12
			],
			"hp": {
				"average": 13,
				"formula": "3d6 + 3"
			},
			"speed": {
				"walk": 30
			},
			"str": 14,
			"dex": 15,
			"con": 13,
			"int": 8,
			"wis": 10,
			"cha": 12,
			"skill": {
				"stealth": "+4"
			},
			"senses": [
				"Darkvision 60 ft."
			],
			"passive": 10,
			"languages": [
				"Common",
				"Sylvan"
			],
			"cr": "1/4",
			"trait": [
				{
					"name": "Siege Monster",
					"entries": [
						"Il noggle infligge danni doppi a oggetti e strutture."
					]
				}
			],
			"action": [
				{
					"name": "Sabotaging Swipe",
					"entries": [
						"{@atkr m} {@hit 4}, portata 5 piedi {@h}6 ({@damage 1d8 + 2}) Danno tagliente. Se il bersaglio indossa un'armatura, è soggetto al seguente effetto. {@actSave dex} {@dc 12}. {@actSaveFail} L'armatura subisce una penalità di -1 alla CA che offre. Il bersaglio può intraprendere un'azione per rimuovere la penalità dalla sua armatura."
					]
				}
			],
			"bonus": [
				{
					"name": "Nimble Escape",
					"entries": [
						"Il noggle esegue l'azione Disingaggiarsi o Nascondersi."
					]
				}
			],
			"environment": [
				"planar, feywild"
			],
			"treasure": [
				"individual"
			],
			"traitTags": [
				"Siege Monster"
			],
			"senseTags": [
				"D"
			],
			"languageTags": [
				"C",
				"S"
			],
			"damageTags": [
				"S"
			],
			"miscTags": [
				"MA"
			],
			"savingThrowForced": [
				"dexterity"
			],
			"hasToken": true,
			"hasFluff": true,
			"hasFluffImages": true
		},
		{
			"name": "Noggle Wild Mage",
			"source": "LFL",
			"size": [
				"S"
			],
			"type": "fey",
			"alignment": [
				"C",
				"N"
			],
			"ac": [
				13
			],
			"hp": {
				"average": 22,
				"formula": "4d6 + 8"
			},
			"speed": {
				"walk": 30
			},
			"str": 11,
			"dex": 16,
			"con": 14,
			"int": 10,
			"wis": 12,
			"cha": 17,
			"save": {
				"con": "+4",
				"cha": "+5"
			},
			"senses": [
				"Darkvision 60 ft."
			],
			"passive": 11,
			"languages": [
				"Common",
				"Sylvan"
			],
			"cr": "1",
			"trait": [
				{
					"name": "Bloodied Wild Magic",
					"entries": [
						"Mentre {@status Bloodied|XPHB}, il noggle ha un {@variantrule Fly Speed|XPHB} di 9 metri e può scegliere che qualsiasi danno inflitto sia danno di Forza."
					]
				}
			],
			"action": [
				{
					"name": "Multiattack",
					"entries": [
						"Il noggle effettua due attacchi, usando Noggling Stick o Befuddling Ray in qualsiasi combinazione."
					]
				},
				{
					"name": "Noggling Stick",
					"entries": [
						"{@atkr m} {@hit 5}, portata 5 piedi {@h}5 ({@damage 1d4 + 3}) Danni contundenti più 2 ({@damage 1d4}) danni psichici."
					]
				},
				{
					"name": "Befuddling Ray",
					"entries": [
						"{@atkr r} {@hit 5}, portata 60 piedi. {@h}6 ({@damage 1d6 + 3}) Danni psichici e il bersaglio sottrae {@dice 1d4} dal successivo tiro salvezza effettuato prima della fine del turno successivo del noggle."
					]
				}
			],
			"environment": [
				"planar, feywild"
			],
			"treasure": [
				"individual"
			],
			"tokenCustom": true,
			"senseTags": [
				"D"
			],
			"actionTags": [
				"Multiattack"
			],
			"languageTags": [
				"C",
				"S"
			],
			"damageTags": [
				"B",
				"Y"
			],
			"miscTags": [
				"MA",
				"RA"
			],
			"hasToken": true,
			"hasFluff": true
		},
		{
			"name": "Shadowmoor Giant",
			"source": "LFL",
			"size": [
				"H"
			],
			"type": "giant",
			"alignment": [
				"C",
				"E"
			],
			"ac": [
				14
			],
			"hp": {
				"average": 172,
				"formula": "15d12 + 75"
			},
			"speed": {
				"walk": 40
			},
			"str": 22,
			"dex": 14,
			"con": 20,
			"int": 7,
			"wis": 19,
			"cha": 8,
			"save": {
				"con": "+8",
				"wis": "+7"
			},
			"senses": [
				"Darkvision 120 ft."
			],
			"passive": 14,
			"languages": [
				"Giant"
			],
			"cr": "8",
			"action": [
				{
					"name": "Multiattack",
					"entries": [
						"Il gigante effettua tre attacchi, usando Tree Club o Boulder in qualsiasi combinazione."
					]
				},
				{
					"name": "Tree Club",
					"entries": [
						"{@atkr m} {@hit 9}, portata 15 piedi {@h}17 ({@damage 2d10 + 6}) Danni contundenti."
					]
				},
				{
					"name": "Boulder",
					"entries": [
						"{@atkr r} {@hit 9}, portata 60/240 piedi. {@h}13 ({@damage 2d6 + 6}) Danni contundenti. Se il bersaglio è una creatura Grande o più piccola, ha la condizione {@condition Prone|XPHB}."
					]
				},
				{
					"name": "Wild Magic Cataclysm {@recharge 5}",
					"entries": [
						"{@actSave dex} {@dc 15}, ogni creatura in un raggio di 20 piedi {@variantrule Sphere [Area of Effect]|XPHB|Sphere} centrata su un punto entro 120 piedi. {@actSaveFail} 28 ({@damage 8d6}) danni (tira {@dice 1d4} per determinare il tipo di danno: 1—Acido; 2—Fuoco; 3—Fulmine; 4—Tuono). {@actSaveSuccess} Danno dimezzato."
					]
				}
			],
			"environment": [
				"planar, feywild"
			],
			"treasure": [
				"arcana"
			],
			"tokenCustom": true,
			"senseTags": [
				"SD"
			],
			"actionTags": [
				"Multiattack"
			],
			"languageTags": [
				"GI"
			],
			"damageTags": [
				"B"
			],
			"miscTags": [
				"AOE",
				"MA",
				"MLW",
				"RA",
				"RCH"
			],
			"conditionInflict": [
				"prone"
			],
			"savingThrowForced": [
				"dexterity"
			],
			"hasToken": true,
			"hasFluff": true
		}
	]
}