{
	"data": [
		{
			"type": "section",
			"name": "DM Screen",
			"entries": [
				{
					"type": "entries",
					"name": "Cover",
					"entries": [
						{
							"type": "image",
							"href": {
								"type": "internal",
								"path": "book/XScreen/XScreen Front.webp"
							},
							"credit": "Joy Ang",
							"width": 1530,
							"height": 340
						}
					],
					"id": "001"
				},
				{
					"type": "entries",
					"name": "Conditions",
					"entries": [
						{
							"type": "statblock",
							"tag": "condition",
							"source": "XPHB",
							"name": "Blinded"
						},
						{
							"type": "statblock",
							"tag": "condition",
							"source": "XPHB",
							"name": "Charmed"
						},
						{
							"type": "statblock",
							"tag": "condition",
							"source": "XPHB",
							"name": "Deafened"
						},
						{
							"type": "statblock",
							"tag": "condition",
							"source": "XPHB",
							"name": "Exhaustion"
						},
						{
							"type": "statblock",
							"tag": "condition",
							"source": "XPHB",
							"name": "Frightened"
						},
						{
							"type": "statblock",
							"tag": "condition",
							"source": "XPHB",
							"name": "Grappled"
						},
						{
							"type": "statblock",
							"tag": "condition",
							"source": "XPHB",
							"name": "Incapacitated"
						},
						{
							"type": "statblock",
							"tag": "condition",
							"source": "XPHB",
							"name": "Invisible"
						},
						{
							"type": "statblock",
							"tag": "condition",
							"source": "XPHB",
							"name": "Paralyzed"
						},
						{
							"type": "statblock",
							"tag": "condition",
							"source": "XPHB",
							"name": "Petrified"
						},
						{
							"type": "statblock",
							"tag": "condition",
							"source": "XPHB",
							"name": "Poisoned"
						},
						{
							"type": "statblock",
							"tag": "condition",
							"source": "XPHB",
							"name": "Prone"
						},
						{
							"type": "statblock",
							"tag": "condition",
							"source": "XPHB",
							"name": "Restrained"
						},
						{
							"type": "statblock",
							"tag": "condition",
							"source": "XPHB",
							"name": "Stunned"
						},
						{
							"type": "statblock",
							"tag": "condition",
							"source": "XPHB",
							"name": "Unconscious"
						}
					],
					"id": "002"
				},
				{
					"type": "entries",
					"name": "Tables",
					"entries": [
						{
							"type": "table",
							"caption": "Improvising Damage",
							"colLabels": [
								"Dice",
								"Examples"
							],
							"colStyles": [
								"col-2 text-center",
								"col-10"
							],
							"rows": [
								[
									"{@damage 1d10}",
									"Bruciato dai carboni, colpito da una libreria che cade, punto da un ago avvelenato"
								],
								[
									"{@damage 2d10}",
									"Colpito da un fulmine, inciampando in un focolare"
								],
								[
									"{@damage 4d10}",
									"Colpito dalla caduta di macerie in un tunnel che crolla, cadendo in una vasca piena di acido"
								],
								[
									"{@damage 10d10}",
									"Schiacciato da pareti compattanti, colpito da lame d'acciaio vorticose, guadando la lava"
								],
								[
									"{@damage 18d10}",
									"Sommerso nella lava, colpito da una fortezza volante che si schianta"
								],
								[
									"{@damage 24d10}",
									"Cadendo in un vortice di fuoco sul Piano Elementale del Fuoco, schiacciato dalle fauci di una creatura divina o di un mostro delle dimensioni di una luna"
								]
							],
							"data": {
								"genTables": {
									"tableChapterIgnore": true
								}
							}
						},
						{
							"type": "table",
							"caption": "Damage Severity and Level",
							"colLabels": [
								"Character Levels",
								"Nuisance",
								"Deadly"
							],
							"colStyles": [
								"col-4 text-center",
								"col-4 text-center",
								"col-4 text-center"
							],
							"rows": [
								[
									"1–4",
									"5 ({@damage 1d10})",
									"11 ({@damage 2d10})"
								],
								[
									"5–10",
									"11 ({@damage 2d10})",
									"22 ({@damage 4d10})"
								],
								[
									"11–16",
									"22 ({@damage 4d10})",
									"55 ({@damage 10d10})"
								],
								[
									"17–20",
									"55 ({@damage 10d10})",
									"99 ({@damage 18d10})"
								]
							],
							"data": {
								"genTables": {
									"tableChapterIgnore": true
								}
							}
						},
						{
							"type": "table",
							"caption": "Actions",
							"colLabels": [
								"Action",
								"Summary"
							],
							"colStyles": [
								"col-2",
								"col-10"
							],
							"rows": [
								[
									"{@action Attack|XPHB}",
									"Attacca con un'arma o un {@variantrule Unarmed Strike|XPHB}."
								],
								[
									"{@action Dash|XPHB}",
									"Per il resto del turno, concediti un movimento extra pari al tuo {@variantrule Speed|XPHB}."
								],
								[
									"{@action Disengage|XPHB}",
									"Il tuo movimento non provoca {@action Opportunity Attack|XPHB|Opportunity Attacks} per il resto del turno."
								],
								[
									"{@action Dodge|XPHB}",
									"Fino all'inizio del tuo prossimo turno, i tiri per colpire contro di te hanno {@variantrule Disadvantage|XPHB} ed effettui tiri salvezza su Destrezza con {@variantrule Advantage|XPHB}. Perdi questo vantaggio se hai la condizione {@condition Incapacitated|XPHB} o se il tuo {@variantrule Speed|XPHB} è 0."
								],
								[
									"{@action Help|XPHB}",
									"Aiuta la prova di abilità o il tiro di attacco di un'altra creatura, oppure presta il primo soccorso."
								],
								[
									"{@action Hide|XPHB}",
									"Effettua una prova di Destrezza ({@skill Stealth|XPHB})."
								],
								[
									"{@action Influence|XPHB}",
									"Effettua una prova di Carisma ({@skill Deception|XPHB}, {@skill Intimidation|XPHB}, {@skill Performance|XPHB} o {@skill Persuasion|XPHB}) o Saggezza ({@skill Animal Handling|XPHB|}) per alterare l'atteggiamento di una creatura."
								],
								[
									"{@action Magic|XPHB}",
									"Lancia un incantesimo, usa un oggetto magico o usa una funzione magica."
								],
								[
									"{@action Ready|XPHB}",
									"Preparati a intraprendere un'azione in risposta a un trigger da te definito."
								],
								[
									"{@action Search|XPHB}",
									"Effettua una prova di Saggezza ({@skill Insight|XPHB}, {@skill Medicine|XPHB}, {@skill Perception|XPHB} o {@skill Survival|XPHB})."
								],
								[
									"{@action Study|XPHB}",
									"Effettua una prova di Intelligenza ({@skill Arcana|XPHB}, {@skill History|XPHB}, {@skill Investigation|XPHB}, {@skill Nature|XPHB} o {@skill Religion|XPHB})."
								],
								[
									"{@action Utilize|XPHB}",
									"Usa un oggetto non magico."
								]
							],
							"footnotes": [
								"{@i See the Player's Handbook rules glossary for full action definitions}"
							],
							"data": {
								"genTables": {
									"tableChapterIgnore": true
								}
							}
						},
						{
							"type": "statblock",
							"tag": "variantrule",
							"source": "XPHB",
							"name": "Long Jump"
						},
						{
							"type": "statblock",
							"tag": "variantrule",
							"source": "XPHB",
							"name": "High Jump"
						},
						{
							"type": "statblock",
							"tag": "status",
							"source": "XPHB",
							"name": "Concentration"
						},
						{
							"type": "table",
							"caption": "Skills",
							"colLabels": [
								"Skill",
								"Ability"
							],
							"colStyles": [
								"col-6",
								"col-6"
							],
							"rows": [
								[
									"{@skill Acrobatics|XPHB}",
									"Destrezza"
								],
								[
									"{@skill Animal Handling|XPHB}",
									"Saggezza"
								],
								[
									"{@skill Arcana|XPHB}",
									"Intelligenza"
								],
								[
									"{@skill Athletics|XPHB}",
									"Forza"
								],
								[
									"{@skill Deception|XPHB}",
									"Carisma"
								],
								[
									"{@skill History|XPHB}",
									"Intelligenza"
								],
								[
									"{@skill Insight|XPHB}",
									"Saggezza"
								],
								[
									"{@skill Intimidation|XPHB}",
									"Carisma"
								],
								[
									"{@skill Investigation|XPHB}",
									"Intelligenza"
								],
								[
									"{@skill Medicine|XPHB}",
									"Saggezza"
								],
								[
									"{@skill Nature|XPHB}",
									"Intelligenza"
								],
								[
									"{@skill Perception|XPHB}",
									"Saggezza"
								],
								[
									"{@skill Performance|XPHB}",
									"Carisma"
								],
								[
									"{@skill Persuasion|XPHB}",
									"Carisma"
								],
								[
									"{@skill Religion|XPHB}",
									"Intelligenza"
								],
								[
									"{@skill Sleight of Hand|XPHB}",
									"Destrezza"
								],
								[
									"{@skill Stealth|XPHB}",
									"Destrezza"
								],
								[
									"{@skill Survival|XPHB}",
									"Saggezza"
								]
							],
							"data": {
								"genTables": {
									"tableChapterIgnore": true
								}
							}
						},
						{
							"type": "entries",
							"name": "Death Saving Throws",
							"entries": [
								"Quando inizi il tuo turno con 0 HP, tira {@dice 1d20} e riesci con 10+.",
								{
									"type": "list",
									"style": "list-hang",
									"items": [
										{
											"type": "item",
											"name": "Third Success",
											"entries": [
												"Diventi {@variantrule Stable|XPHB}."
											]
										},
										{
											"type": "item",
											"name": "Third Failure",
											"entries": [
												"Tu muori."
											]
										},
										{
											"type": "item",
											"name": "Rolling a 1",
											"entries": [
												"Conta come due fallimenti."
											]
										},
										{
											"type": "item",
											"name": "Rolling a 20",
											"entries": [
												"Recuperi 1 Punto Ferita."
											]
										}
									]
								},
								"Se subisci danni a 0 HP, conta come un fallimento {@variantrule Death Saving Throw|XPHB|Death Save} o due fallimenti se il danno proviene da un {@variantrule Critical Hit|XPHB}."
							],
							"data": {
								"variantRuleInclude": {
									"ruleType": "C"
								}
							},
							"id": "004"
						},
						{
							"type": "table",
							"caption": "Object Armor Class",
							"colLabels": [
								"AC",
								"Substance"
							],
							"colStyles": [
								"col-2 text-center",
								"col-10"
							],
							"rows": [
								[
									"11",
									"Stoffa, carta, corda"
								],
								[
									"13",
									"Cristallo, vetro, ghiaccio"
								],
								[
									"15",
									"Wood"
								],
								[
									"17",
									"Calcolo"
								],
								[
									"19",
									"Ferro, acciaio"
								],
								[
									"21",
									"Mithral"
								],
								[
									"23",
									"Adamantino"
								]
							],
							"data": {
								"genTables": {
									"tableChapterIgnore": true
								}
							}
						},
						{
							"type": "table",
							"caption": "Object Hit Points",
							"colLabels": [
								"Size",
								"Fragile",
								"Resilient"
							],
							"colStyles": [
								"col-6",
								"col-3",
								"col-3"
							],
							"rows": [
								[
									"Piccolo (bottiglia, lucchetto)",
									"2 ({@dice 1d4})",
									"5 ({@dice 2d4})"
								],
								[
									"Piccolo (petto, liuto)",
									"3 ({@dice 1d6})",
									"10 ({@dice 3d6})"
								],
								[
									"Medio (botte, lampadario)",
									"4 ({@dice 1d8})",
									"18 ({@dice 4d8})"
								],
								[
									"Grande (carrello, tavolo da pranzo)",
									"5 ({@dice 1d10})",
									"27 ({@dice 5d10})"
								]
							],
							"data": {
								"genTables": {
									"tableChapterIgnore": true
								}
							}
						},
						{
							"type": "table",
							"caption": "Food, Drink, and Lodging",
							"colLabels": [
								"Item",
								"Cost"
							],
							"colStyles": [
								"col-8",
								"col-4 text-right"
							],
							"rows": [
								[
									"{@item Ale (mug)|XPHB}",
									"4 CP"
								],
								[
									"{@item Bread (loaf)|XPHB}",
									"2 CP"
								],
								[
									"{@item Cheese (wedge)|XPHB}",
									"1 SP"
								],
								[
									"{@i Inn Stay per Day}",
									""
								],
								{
									"type": "row",
									"style": "row-indent-first",
									"row": [
										"Squalid",
										"7 CP"
									]
								},
								{
									"type": "row",
									"style": "row-indent-first",
									"row": [
										"Poor",
										"1 SP"
									]
								},
								{
									"type": "row",
									"style": "row-indent-first",
									"row": [
										"Modest",
										"5 SP"
									]
								},
								{
									"type": "row",
									"style": "row-indent-first",
									"row": [
										"Comfortable",
										"8 SP"
									]
								},
								{
									"type": "row",
									"style": "row-indent-first",
									"row": [
										"Wealthy",
										"2 GP"
									]
								},
								{
									"type": "row",
									"style": "row-indent-first",
									"row": [
										"Aristocratic",
										"4 GP"
									]
								},
								[
									"{@i Meal}",
									""
								],
								{
									"type": "row",
									"style": "row-indent-first",
									"row": [
										"Squalid",
										"1 CP"
									]
								},
								{
									"type": "row",
									"style": "row-indent-first",
									"row": [
										"Poor",
										"2 CP"
									]
								},
								{
									"type": "row",
									"style": "row-indent-first",
									"row": [
										"Modest",
										"1 SP"
									]
								},
								{
									"type": "row",
									"style": "row-indent-first",
									"row": [
										"Comfortable",
										"2 SP"
									]
								},
								{
									"type": "row",
									"style": "row-indent-first",
									"row": [
										"Wealthy",
										"3 SP"
									]
								},
								{
									"type": "row",
									"style": "row-indent-first",
									"row": [
										"Aristocratic",
										"6 SP"
									]
								},
								[
									"{@i Wine (bottle)}",
									""
								],
								{
									"type": "row",
									"style": "row-indent-first",
									"row": [
										"{@item Common Wine (bottle)|XPHB|Common}",
										"2 SP"
									]
								},
								{
									"type": "row",
									"style": "row-indent-first",
									"row": [
										"{@item Fine Wine (bottle)|XPHB|Fine}",
										"10 GP"
									]
								}
							],
							"data": {
								"genTables": {
									"tableChapterIgnore": true
								}
							}
						},
						{
							"type": "table",
							"caption": "Typical Difficulty Classes",
							"colLabels": [
								"Task Difficulty",
								"DC"
							],
							"colStyles": [
								"col-10",
								"col-2 text-center"
							],
							"rows": [
								[
									"Molto facile",
									"5"
								],
								[
									"Easy",
									"10"
								],
								[
									"Medio",
									"15"
								],
								[
									"Hard",
									"20"
								],
								[
									"Molto difficile",
									"25"
								],
								[
									"Quasi impossibile",
									"30"
								]
							],
							"data": {
								"genTables": {
									"tableChapterIgnore": true
								}
							}
						},
						{
							"type": "table",
							"caption": "Light Sources",
							"colLabels": [
								"Source",
								"Bright Light",
								"Dim Light",
								"Duration"
							],
							"colStyles": [
								"col-3",
								"col-3",
								"col-3",
								"col-3"
							],
							"rows": [
								[
									"{@item Candle|XPHB}",
									"5 feet",
									"+5 piedi",
									"1 hour"
								],
								[
									"{@item Lamp|XPHB}",
									"15 feet",
									"+30 piedi",
									"6 ore"
								],
								[
									"{@item Bullseye Lantern|XPHB|Lantern, Bullseye}",
									"60-foot {@variantrule Cone [Area of Effect]|XPHB|Cone}",
									"+60 piedi",
									"6 ore"
								],
								[
									"{@item Hooded Lantern|XPHB|Lantern, Hooded}",
									"30 piedi (nessuno con il cofano abbassato)",
									"+30 piedi (5 piedi con cofano abbassato)",
									"6 ore"
								],
								[
									"{@item Torch|XPHB}",
									"20 feet",
									"+20 piedi",
									"1 hour"
								]
							],
							"data": {
								"genTables": {
									"tableChapterIgnore": true
								}
							}
						},
						{
							"type": "table",
							"caption": "Obscured Areas",
							"colLabels": [
								"Obscureness",
								"Effect",
								"Examples"
							],
							"colStyles": [
								"col-3",
								"col-5",
								"col-4"
							],
							"rows": [
								[
									"{@variantrule Lightly Obscured|XPHB}",
									"Le creature hanno {@variantrule Disadvantage|XPHB} prove di Saggezza ({@skill Perception|XPHB}) che si basano sulla vista",
									"{@variantrule Dim Light|XPHB}, nebbia irregolare, fogliame moderato"
								],
								[
									"{@variantrule Heavily Obscured|XPHB}",
									"Le creature hanno la condizione {@condition Blinded|XPHB}.",
									"{@variantrule Darkness|XPHB}, nebbia fitta, fogliame denso"
								]
							],
							"data": {
								"genTables": {
									"tableChapterIgnore": true
								}
							}
						},
						{
							"type": "table",
							"caption": "Travel Pace",
							"colLabelRows": [
								[
									"",
									{
										"type": "cellHeader",
										"width": 3,
										"entry": "Distanza percorsa per...",
										"style": "th-skewer"
									},
									""
								],
								[
									"Pace",
									"Minute",
									"Hour",
									"Day",
									"Effect"
								]
							],
							"colStyles": [
								"col-2",
								"col-2",
								"col-2",
								"col-2",
								"col-4"
							],
							"rows": [
								[
									"Fast",
									"400 feet",
									"4 miglia",
									"30 miglia",
									"{@variantrule Disadvantage|XPHB} alle prove di Saggezza ({@skill Perception|XPHB} o {@skill Survival|XPHB}) e Destrezza ({@skill Stealth|XPHB})"
								],
								[
									"Normale",
									"300 feet",
									"3 miglia",
									"24 miglia",
									"{@variantrule Disadvantage|XPHB} alle prove di Destrezza ({@skill Stealth|XPHB})."
								],
								[
									"Slow",
									"200 feet",
									"2 miglia",
									"18 miglia",
									"{@variantrule Advantage|XPHB} alle prove di Saggezza ({@skill Perception|XPHB} o {@skill Survival|XPHB})."
								]
							],
							"data": {
								"genTables": {
									"tableChapterIgnore": true
								}
							}
						},
						{
							"type": "table",
							"caption": "Travel Terrain",
							"colLabels": [
								"Terrain",
								"Maximum Pace",
								"Encounter Distance",
								"Foraging DC",
								"Navigation DC",
								"Search DC"
							],
							"colStyles": [
								"col-2",
								"col-2 text-center",
								"col-2 text-center",
								"col-2 text-center",
								"col-2 text-center",
								"col-2 text-center"
							],
							"rows": [
								[
									"artico",
									"Veloce*",
									"{@dice 6d6 × 10} feet",
									"20",
									"10",
									"10"
								],
								[
									"Costiero",
									"Normale",
									"{@dice 2d10 × 10} feet",
									"10",
									"5",
									"15"
								],
								[
									"Deserto",
									"Normale",
									"{@dice 6d6 × 10} feet",
									"20",
									"10",
									"10"
								],
								[
									"Foresta",
									"Normale",
									"{@dice 2d8 × 10} feet",
									"10",
									"15",
									"15"
								],
								[
									"Prateria",
									"Fast",
									"{@dice 6d6 × 10} feet",
									"15",
									"5",
									"15"
								],
								[
									"Hill",
									"Normale",
									"{@dice 2d10 × 10} feet",
									"15",
									"10",
									"15"
								],
								[
									"Montagna",
									"Slow",
									"{@dice 4d10 × 10} feet",
									"20",
									"15",
									"20"
								],
								[
									"Pantano",
									"Slow",
									"{@dice 2d8 × 10} feet",
									"10",
									"15",
									"20"
								],
								[
									"Sottosuolo",
									"Normale",
									"{@dice 2d6 × 10} feet",
									"20",
									"10",
									"20"
								],
								[
									"Urbano",
									"Normale",
									"{@dice 2d6 × 10} feet",
									"20",
									"15",
									"15"
								],
								[
									"A base d'acqua",
									"Speciale†",
									"{@dice 6d6 × 10} feet",
									"15",
									"10",
									"15"
								]
							],
							"footnotes": [
								"*Appropriate equipment (such as skis) is necessary to keep up a Fast pace in Arctic terrain.",
								"†Characters' rate of travel while waterborne depends on the vehicle carrying them."
							],
							"data": {
								"genTables": {
									"tableChapterIgnore": true
								}
							}
						},
						{
							"type": "table",
							"caption": "Cover",
							"colLabels": [
								"Cover Degree",
								"Benefit to Target"
							],
							"colStyles": [
								"col-3",
								"col-9"
							],
							"rows": [
								[
									"Mezza copertura",
									"Bonus di +2 ai tiri salvezza su CA e Destrezza"
								],
								[
									"Copertura a tre quarti",
									"Bonus di +5 ai tiri salvezza su CA e Destrezza"
								],
								[
									"Copertura totale",
									"Non può essere preso di mira direttamente"
								]
							],
							"data": {
								"genTables": {
									"tableChapterIgnore": true
								}
							}
						},
						{
							"type": "table",
							"caption": "Audible Distance",
							"colLabels": [
								"Noise",
								"Distance"
							],
							"colStyles": [
								"col-6",
								"col-6"
							],
							"rows": [
								[
									"Cercando di stare zitto",
									"{@dice 2d6 × 5} feet"
								],
								[
									"Livello di rumore normale",
									"{@dice 2d6 × 10} feet"
								],
								[
									"Molto rumoroso",
									"{@dice 2d6 × 50} feet"
								]
							],
							"data": {
								"genTables": {
									"tableChapterIgnore": true
								}
							}
						},
						{
							"type": "table",
							"caption": "Visibility Outdoors",
							"colLabels": [
								"Conditions",
								"Distance"
							],
							"colStyles": [
								"col-6",
								"col-6"
							],
							"rows": [
								[
									"Giornata limpida, senza ostacoli",
									"2 miglia (40 miglia da un'altitudine)"
								],
								[
									"Rain ({@variantrule Lightly Obscured|XPHB})",
									"1 mile"
								],
								[
									"Fog ({@variantrule Lightly Obscured|XPHB})",
									"Da 100 a 300 piedi"
								]
							],
							"data": {
								"genTables": {
									"tableChapterIgnore": true
								}
							}
						},
						{
							"type": "tableGroup",
							"name": "Weather",
							"tables": [
								{
									"type": "table",
									"caption": "Weather",
									"colLabels": [
										"1d20",
										"Temperature"
									],
									"colStyles": [
										"col-2 text-center",
										"col-10"
									],
									"rows": [
										[
											"1–14",
											"Normale per la stagione"
										],
										[
											"15–17",
											"{@dice 1d4 × 10} gradi Fahrenheit più freddi"
										],
										[
											"18–20",
											"{@dice 1d4 × 10} gradi Fahrenheit più caldi"
										]
									],
									"data": {
										"genTables": {
											"tableChapterIgnore": true
										}
									}
								},
								{
									"type": "table",
									"colLabels": [
										"1d20",
										"Wind",
										"Precipitation"
									],
									"colStyles": [
										"col-2 text-center",
										"col-2",
										"col-8"
									],
									"rows": [
										[
											"1–12",
											"None",
											"None"
										],
										[
											"13–17",
											"Leggero",
											"Pioggia leggera o nevicate leggere"
										],
										[
											"18–20",
											"Forte",
											"Forti piogge o forti nevicate"
										]
									],
									"data": {
										"genTables": {
											"tableChapterIgnore": true
										}
									}
								}
							]
						}
					],
					"id": "003"
				}
			],
			"id": "000"
		}
	]
}